jiweicode/书写树的多种遍历算法.py
jiweicode/实现链表逆置.py
jiweicode/排序算法.py
jiweicode/数对应二进制中1的个数.py
jiweicode/面试题10.01合并排序后的数组.py
jiweicode/面试题57.和为s的连续正数序列.py
jiweicode/面试题59.队列的最大值.py
jiweicode/题目1.两数之和.py
jiweicode/题目10.正则表达式匹配.py
jiweicode/题目100.相同的树.py
jiweicode/题目101.对称二叉树.py
jiweicode/题目1013.将数组分成和相等的三个部分.py
jiweicode/题目102.二叉树的层次遍历.py
jiweicode/题目104.二叉树的最大深度.py
jiweicode/题目105.从前序与中序遍历序列构造二叉树.py
jiweicode/题目1071. 字符串的最大公因子.py
jiweicode/题目11.盛最多水的容器.py
jiweicode/题目110.平衡二叉树.py
jiweicode/题目1103.分糖果 II.py
jiweicode/题目112.路径总和.py
jiweicode/题目113.路径总和2.py
jiweicode/题目114.二叉树展开为链表.py
jiweicode/题目121.买卖股票的最佳时机.py
jiweicode/题目124.二叉树中的最大路径和.py
jiweicode/题目126.Word Ladder II.py
jiweicode/题目128.最长连续序列.py
jiweicode/题目129.求根到叶子节点数字之和（打卡）.py
jiweicode/题目136.只出现一次的数字.py
jiweicode/题目139.单词拆分.py
jiweicode/题目141.环形链表.py
jiweicode/题目142.环形链表 II.py
jiweicode/题目146.LRU缓存机制.py
jiweicode/题目148.排序链表.py
jiweicode/题目15.三数之和.py
jiweicode/题目152.乘积最大子序列.py
jiweicode/题目155.最小栈.py
jiweicode/题目160.相交链表.py
jiweicode/题目169.求众数.py
jiweicode/题目17.电话号码的字母组合.py
jiweicode/题目19.删除链表的倒数第N个节点.py
jiweicode/题目198.打家劫舍.py
jiweicode/题目2.两数相加.py
jiweicode/题目20.有效的括号.py
jiweicode/题目200.岛屿的个数.py
jiweicode/题目206.反转链表.py
jiweicode/题目207.课程表.py
jiweicode/题目208.实现 Trie (前缀树).py
jiweicode/题目21.合并两个有序链表.py
jiweicode/题目215.数组中的第K个最大元素.py
jiweicode/题目22.括号生成.py
jiweicode/题目221.最大正方形.py
jiweicode/题目222.完全二叉树的结点个数.py
jiweicode/题目225.用队列实现栈.py
jiweicode/题目226.翻转二叉树.py
jiweicode/题目23.合并K个排序链表.py
jiweicode/题目230.二叉搜索树中第K小的元素.py
jiweicode/题目234.回文链表.py
jiweicode/题目235.二叉搜索树的最近公共祖先.py
jiweicode/题目236.二叉树的最近公共祖先.py
jiweicode/题目238.除自身以外数组的乘积.py
jiweicode/题目239.滑动窗口最大值.py
jiweicode/题目240.搜索二维矩阵 II.py
jiweicode/题目253.会议室 II.py
jiweicode/题目257.二叉树的所有路径.py
jiweicode/题目279.完全平方数.py
jiweicode/题目283.移动零.py
jiweicode/题目287.寻找重复数.py
jiweicode/题目297.二叉树的序列化和反序列化.py
jiweicode/题目3.无重复字符的最长字串.py
jiweicode/题目300.最长上升子序列.py
jiweicode/题目301.删除多余括号.py
jiweicode/题目301.删除无效的括号.py
jiweicode/题目309.最佳买卖股票时机含冷冻期.py
jiweicode/题目31.下一个排列.py
jiweicode-0.0.1.dist-info/METADATA
jiweicode-0.0.1.dist-info/WHEEL
jiweicode-0.0.1.dist-info/top_level.txt
jiweicode-0.0.1.dist-info/RECORD
